simple_flatten_json_py/__init__.py
simple_flatten_json_py/simple_flatten_json.py
simple_flatten_json-0.0.9.dist-info/LICENSE
simple_flatten_json-0.0.9.dist-info/METADATA
simple_flatten_json-0.0.9.dist-info/WHEEL
simple_flatten_json-0.0.9.dist-info/top_level.txt
simple_flatten_json-0.0.9.dist-info/RECORD
