Metadata-Version: 2.1
Name: simple-flatten-json
Version: 0.0.9
Summary: For flattening complex JSONs
Home-page: https://github.com/at-75/simple_json_flatten_py
Author: Abhishek Thakur
Classifier: Programming Language :: Python :: 3
Classifier: License :: OSI Approved :: MIT License
Classifier: Operating System :: OS Independent
Requires-Python: <4,>=3.7
License-File: LICENSE
